<annotation>
	<folder>unicycle1</folder>
	<filename>362_0013.jpg</filename>
	<path>/home/somnath/Documents/Project/darkflow-master/new_model_data/unicycle1/362_0013.jpg</path>
	<source>
		<database>Unknown</database>
	</source>
	<size>
		<width>475</width>
		<height>417</height>
		<depth>3</depth>
	</size>
	<segmented>0</segmented>
	<object>
		<name>uni cycle</name>
		<pose>Unspecified</pose>
		<truncated>0</truncated>
		<difficult>0</difficult>
		<bndbox>
			<xmin>185</xmin>
			<ymin>208</ymin>
			<xmax>280</xmax>
			<ymax>386</ymax>
		</bndbox>
	</object>
</annotation>
